{
  "tests": [
    {
      "category": "public",
      "input": "Prog1\n",
      "output": "<P> nao\n<r> nao\n<o> sim\n<g> nao\n<1> nao\n"
    }
  ],
  "be306128e024488d3ab687ef96af1caa": {
    "timestamp": "2016-03-17T12:10:43.991400",
    "feedback": "",
    "summary": ".FF"
  },
  "activity_revision": "1.0.1",
  "key": "1497C58A000000",
  "last_commit": "c643f28739551ddc0ccebe3f83640a7d",
  "c643f28739551ddc0ccebe3f83640a7d": {
    "timestamp": "2016-03-17T12:12:01.308900",
    "feedback": "",
    "summary": "..."
  }
}